st_text_annotator/__init__.py
st_text_annotator/frontend/.env
st_text_annotator/frontend/.prettierrc
st_text_annotator/frontend/build/asset-manifest.json
st_text_annotator/frontend/build/index.html
st_text_annotator/frontend/build/static/js/main.0e3a6e40.js
st_text_annotator/frontend/build/static/js/main.0e3a6e40.js.LICENSE.txt
st_text_annotator/frontend/build/static/js/main.0e3a6e40.js.map
st_text_annotator/frontend/package.json
st_text_annotator/frontend/public/index.html
st_text_annotator/frontend/src/components/Annotation.tsx
st_text_annotator/frontend/src/helpers/annotationHelpers.ts
st_text_annotator/frontend/src/index.tsx
st_text_annotator/frontend/src/react-app-env.d.ts
st_text_annotator/frontend/src/reducers/annotationReducer.tsx
st_text_annotator/frontend/src/types.ts
st_text_annotator/frontend/src/utils/StreamlitProvider.tsx
st_text_annotator/frontend/src/utils/useNullableRenderData.ts
st_text_annotator/frontend/tsconfig.json
st_text_annotator-0.3.4.dist-info/LICENSE
st_text_annotator-0.3.4.dist-info/METADATA
st_text_annotator-0.3.4.dist-info/WHEEL
st_text_annotator-0.3.4.dist-info/RECORD
