Metadata-Version: 2.1
Name: st-text-annotator
Version: 0.3.4
Summary: Component for annotating text for NLP resolution
License: MIT
Keywords: streamlit,text,annotation,nlp
Author: Robin Marquet
Author-email: robin.marquet@epitech.eu
Requires-Python: >=3.8, !=2.7.*, !=3.0.*, !=3.1.*, !=3.2.*, !=3.3.*, !=3.4.*, !=3.5.*, !=3.6.*, !=3.7.*
Classifier: License :: OSI Approved :: MIT License
Classifier: Operating System :: OS Independent
Classifier: Programming Language :: Python :: 3
Classifier: Programming Language :: Python :: 3.8
Classifier: Programming Language :: Python :: 3.9
Classifier: Programming Language :: Python :: 3.10
Classifier: Programming Language :: Python :: 3.11
Requires-Dist: streamlit (==1.21.0)
